podcatch/Episode.py
podcatch/Parameters.py
podcatch/Podcast.py
podcatch/Utilities.py
podcatch/__init__.py
podcatch/fetchPodcasts.py
podcatch/config/podcasts.list
podcatch/config/podcatch.conf
podcatch-0.0.14.dist-info/DESCRIPTION.rst
podcatch-0.0.14.dist-info/METADATA
podcatch-0.0.14.dist-info/RECORD
podcatch-0.0.14.dist-info/WHEEL
podcatch-0.0.14.dist-info/entry_points.txt
podcatch-0.0.14.dist-info/metadata.json
podcatch-0.0.14.dist-info/top_level.txt
