Metadata-Version: 2.0
Name: podcatch
Version: 0.0.14
Summary: Podcast fetcher and tagger
Home-page: https://github.com/jlallouette/PodCatch
Author: Jules Lallouette
Author-email: jules@lallouette.fr
License: GNU GPL v3
Keywords: podcast RSS download tagger
Platform: UNKNOWN
Requires-Dist: appdirs
Requires-Dist: feedparser
Requires-Dist: mutagen
Requires-Dist: requests
Requires-Dist: tqdm
